ECOv003_granules/ECOv003_granules.py
ECOv003_granules/L1CTRAD.py
ECOv003_granules/L2TLSTE.py
ECOv003_granules/L2TSTARS.py
ECOv003_granules/L3TETAUX.py
ECOv003_granules/L3TJET.py
ECOv003_granules/L3TMET.py
ECOv003_granules/L3TSEB.py
ECOv003_granules/L3TSM.py
ECOv003_granules/L4TESI.py
ECOv003_granules/L4TWUE.py
ECOv003_granules/__init__.py
ECOv003_granules/colors.py
ECOv003_granules/constants.py
ECOv003_granules/granule.py
ECOv003_granules/open_granule.py
ECOv003_granules/tiled_granule.py
ECOv003_granules/version.py
ECOv003_granules/write_L3T_ETAUX.py
ECOv003_granules/write_L3T_JET.py
ECOv003_granules/write_L3T_MET.py
ECOv003_granules/write_L3T_SEB.py
ECOv003_granules/write_L3T_SM.py
ECOv003_granules/write_L4T_ESI.py
ECOv003_granules/write_L4T_WUE.py
ECOv003_granules/write_XML_metadata.py
ECOv003_granules/timer/__init__.py
ECOv003_granules/timer/timer.py
ecov003_granules-1.13.1.dist-info/licenses/LICENSE
ecov003_granules-1.13.1.dist-info/METADATA
ecov003_granules-1.13.1.dist-info/WHEEL
ecov003_granules-1.13.1.dist-info/top_level.txt
ecov003_granules-1.13.1.dist-info/RECORD
